utilities/__init__.py
utilities/fermi_cat.py
utilities/ftp.py
utilities/healpix.py
utilities/ipynb_docgen.py
utilities/power_spectrum_fft.py
utilities/skydir.py
utilities/timer.py
utilities/uplots.py
wtlike/__init__.py
wtlike/_nbdev.py
wtlike/bayesian.py
wtlike/cell_data.py
wtlike/config.py
wtlike/data_man.py
wtlike/effective_area.py
wtlike/exposure.py
wtlike/lightcurve.py
wtlike/load_data.py
wtlike/load_gti.py
wtlike/loglike.py
wtlike/main.py
wtlike/poisson.py
wtlike/select_data.py
wtlike/simulation.py
wtlike/source_data.py
wtlike/sources.py
wtlike/time_series.py
wtlike/tutorial.py
wtlike/weights.py
wtlike-0.4.4.dist-info/LICENSE
wtlike-0.4.4.dist-info/METADATA
wtlike-0.4.4.dist-info/WHEEL
wtlike-0.4.4.dist-info/entry_points.txt
wtlike-0.4.4.dist-info/top_level.txt
wtlike-0.4.4.dist-info/RECORD
