Metadata-Version: 2.1
Name: wtlike
Version: 0.4.4
Summary: Time-dependent analysis of point sources in Fermi-LAT data
Home-page: https://github.com/tburnett/wtlike/tree/master/
Author: Toby Burnett
Author-email: tburnett@uw.edu
License: Apache Software License 2.0
Keywords: fermi gamma-rays
Platform: UNKNOWN
Classifier: Development Status :: 5 - Production/Stable
Classifier: Intended Audience :: Developers
Classifier: License :: OSI Approved :: Apache Software License
Classifier: Natural Language :: English
Classifier: Programming Language :: Python :: 3.7
Classifier: Programming Language :: Python :: 3.8
Classifier: Programming Language :: Python :: 3.9
Requires-Python: >=3.7
License-File: LICENSE
Requires-Dist: matplotlib
Requires-Dist: pandas
Requires-Dist: scipy (>=1.7.3)
Requires-Dist: astropy (>4.0)
Requires-Dist: healpy
